<?xml version="1.0" encoding="UFT-8" ?>
<!--
cell: 跳转npc配置， npc: npc_template表中的id，map_dest: +分隔三个参数分别表示（地图，坐标x，坐标y）
-->
<data>
  <cell npc="9001" map_dest="1002+6+4"/>  <!-- 新手村去主城 -->
  <cell npc="9003" map_dest="1001+94+85"/>  <!-- 主城去新手村 -->
  <cell npc="9002" map_dest="1002+7+80"/>  <!-- 绿影森林去主城 -->
  <cell npc="9004" map_dest="1003+113+6"/>  <!-- 主城去绿影森林 -->
  <cell npc="9005" map_dest="1004+8+10"/>  <!-- 绿影森林去幽灵谷 -->
  <cell npc="9006" map_dest="1003+10+76"/>  <!-- 幽灵谷去绿影森林 -->
  <cell npc="9007" map_dest="1005+13+82"/>  <!-- 幽灵谷去失心荒地 -->
  <cell npc="9008" map_dest="1004+118+81"/>  <!-- 失心荒地去幽灵谷 -->
  <cell npc="9009" map_dest="1006+60+5"/>  <!-- 失心荒地去赤道沙漠 -->
  <cell npc="9010" map_dest="1005+110+5"/>  <!-- 赤道沙漠去失心荒地 -->
  <cell npc="9011" map_dest="1007+4+54"/>  <!-- 赤道沙漠去翔凤峡谷 -->
  <cell npc="9012" map_dest="1006+143+22"/>  <!-- 翔凤峡谷去赤道沙漠 -->
  <cell npc="9013" map_dest="1008+70+80"/>  <!-- 翔凤峡谷去森罗要塞 -->
  <cell npc="9014" map_dest="1007+78+4"/>  <!-- 森罗要塞去翔凤峡谷 -->
  <cell npc="9015" map_dest="1009+5+75"/>  <!-- 森罗要塞去赤茫丘陵 -->
  <cell npc="9016" map_dest="1008+144+8"/>  <!-- 赤茫丘陵去森罗要塞 -->
  <cell npc="9017" map_dest="1003+117+80"/>  <!-- 赤道沙漠去绿影森林 -->
  <cell npc="9018" map_dest="1006+80+81"/>  <!-- 绿影森林去赤道沙漠 -->
  <cell npc="9019" map_dest="1010+110+81"/>  <!-- 主城去死亡花园 -->
  <cell npc="9020" map_dest="1002+145+77"/>  <!-- 死亡花园去主城 -->
  <cell npc="9021" map_dest="1011+18+81"/>  <!-- 死亡花园去深渊地穴 -->
  <cell npc="9022" map_dest="1010+137+8"/>  <!-- 深渊地穴去死亡花园 -->
  <cell npc="9032" map_dest="1012+9+83"/>  <!-- 深渊地穴去冻海之滨 -->
  <cell npc="9023" map_dest="1011+142+38"/>  <!-- 冻海之滨去深渊地穴 -->
  <cell npc="9024" map_dest="1013+22+82"/>  <!-- 冻海之滨去接天山脉 -->
  <cell npc="9025" map_dest="1012+128+5"/>  <!-- 接天山脉去冻海之滨 -->
  <cell npc="9026" map_dest="1014+27+81"/>  <!-- 主城去灼烧火山 -->
  <cell npc="9027" map_dest="1002+146+30"/>  <!-- 灼烧火山去主城 -->
  <cell npc="9028" map_dest="1015+16+81"/>  <!-- 灼烧火山去暗黑神殿 -->
  <cell npc="9029" map_dest="1014+134+78"/>  <!-- 暗黑神殿去灼烧火山 -->
  <cell npc="9030" map_dest="1016+1+1"/>  <!-- 暗黑神殿去英灵殿 -->
  <cell npc="9031" map_dest="1015+1+1"/>  <!-- 英灵殿去暗黑神殿 -->
  <cell npc="9033" map_dest="1010+10+81"/>  <!-- 赤茫丘陵去死亡花园 -->
  <cell npc="9034" map_dest="1009+144+66"/>  <!-- 死亡花园去赤茫丘陵 -->  
  


  
  
  
  

</data>

